.gitignore
LICENSE
README.md
setup.py
olha/SequenceGeneration.cpp
olha/SequenceGeneration.h
olha/__init__.py
olha/generation.py
olha/main.cpp
olha/utils.h
olha/utils.py
olha.egg-info/PKG-INFO
olha.egg-info/SOURCES.txt
olha.egg-info/dependency_links.txt
olha.egg-info/not-zip-safe
olha.egg-info/top_level.txt