Metadata-Version: 2.1
Name: olha
Version: 0.1.1
Summary: Fast generation of TCR/BCR sequences with olga
Home-page: UNKNOWN
Author: Thomas Dupic
Author-email: dupic.thomas@gmail.com
License: MIT
Platform: UNKNOWN
Classifier: Development Status :: 3 - Alpha
Classifier: Intended Audience :: Developers
Classifier: Intended Audience :: Healthcare Industry
Classifier: Intended Audience :: Science/Research
Classifier: Topic :: Scientific/Engineering :: Bio-Informatics
Classifier: Topic :: Scientific/Engineering :: Physics
Classifier: Topic :: Scientific/Engineering :: Medical Science Apps.
Classifier: Natural Language :: English
Classifier: Programming Language :: Python :: 3.6
